pydingbot/__init__.py
pydingbot/main.py
pydingbot-0.0.3.dist-info/LICENSE
pydingbot-0.0.3.dist-info/METADATA
pydingbot-0.0.3.dist-info/WHEEL
pydingbot-0.0.3.dist-info/top_level.txt
pydingbot-0.0.3.dist-info/RECORD
