Metadata-Version: 2.1
Name: pydingbot
Version: 0.0.3
Summary: A package to make dingbot easily to use
Home-page: https://github.com/Clarmy/pydingbot
Author: Wentao Li
Author-email: clarmylee92510@gmail.com
License: UNKNOWN
Platform: UNKNOWN
Classifier: Programming Language :: Python :: 3
Requires-Python: >=3.6
Requires-Dist: pytest (==6.1.2)
Requires-Dist: requests (==2.25.0)
